aiutils-0.0.1.data/scripts/ml_utils
mlutils/__init__.py
mlutils/model_comparison/__init__.py
mlutils/model_comparison/_classification.py
mlutils/model_comparison/_regression.py
aiutils-0.0.1.dist-info/LICENSE
aiutils-0.0.1.dist-info/METADATA
aiutils-0.0.1.dist-info/WHEEL
aiutils-0.0.1.dist-info/top_level.txt
aiutils-0.0.1.dist-info/RECORD
