Metadata-Version: 2.1
Name: aiutils
Version: 0.0.1
Summary: A python library to automate different sets of tedious tasks used daily in machine learning.
Home-page: UNKNOWN
License: UNKNOWN
Platform: UNKNOWN
Classifier: Programming Language :: Python :: 3
Classifier: License :: OSI Approved :: MIT License
Classifier: Operating System :: OS Independent
Requires-Python: >=3.5
Requires-Dist: numpy (==1.16.0)
Requires-Dist: pandas (==0.24.2)
Requires-Dist: scikit-learn (==0.20.3)
